ou_wbpy/__init__.py
ou_wbpy/api.py
ou_wbpy-0.0.1.dist-info/LICENSE
ou_wbpy-0.0.1.dist-info/METADATA
ou_wbpy-0.0.1.dist-info/WHEEL
ou_wbpy-0.0.1.dist-info/top_level.txt
ou_wbpy-0.0.1.dist-info/RECORD
