Metadata-Version: 2.1
Name: ou-wbpy
Version: 0.0.1
Summary: LLM plugin for running models using llama.cpp
Author: Tony Hirst
License: MIT
Project-URL: Homepage, https://github.com/innovationOUtside/ou-wbpy
License-File: LICENSE
Requires-Dist: wbpy
Requires-Dist: pandas
